dlpx/__init__.py
dlpx/virtualization/__init__.py
dlpx/virtualization/api/VERSION
dlpx/virtualization/api/__init__.py
dlpx/virtualization/api/common_pb2.py
dlpx/virtualization/api/libs_pb2.py
dlpx/virtualization/api/libs_service_pb2.py
dlpx/virtualization/api/libs_service_pb2_grpc.py
dlpx/virtualization/api/platform_pb2.py
dlpx/virtualization/api/platform_service_pb2.py
dlpx/virtualization/api/platform_service_pb2_grpc.py
dvp_api-1.9.0.dist-info/LICENSE
dvp_api-1.9.0.dist-info/METADATA
dvp_api-1.9.0.dist-info/WHEEL
dvp_api-1.9.0.dist-info/top_level.txt
dvp_api-1.9.0.dist-info/RECORD
