Metadata-Version: 2.1
Name: dvp-api
Version: 1.9.0
Summary: Delphix Virtualization Platform API
Home-page: https://developer.delphix.com
Author: Delphix
Author-email: virtualization-plugins@delphix.com
Keywords: virtualization plugin
Classifier: Development Status :: 5 - Production/Stable
Classifier: Programming Language :: Python
Classifier: Programming Language :: Python :: 3.11
Classifier: License :: OSI Approved :: Apache Software License
Classifier: Operating System :: OS Independent
Requires-Python: ==3.11.*
License-File: LICENSE
Requires-Dist: protobuf==4.25.5
